[
    {
        "timestamp_utc": "2021-03-16 22:30:28",
        "transaction_id": "840a7307-c211-bfa6-343b-53d42c1ba791",
        "asset_id": "1G1FY6S03K4108670",
        "timestamp": 1615933828,
        "synthesis.eventSource": "DOORS_LOCKED",
        "originator.id": "000000000000000000000000500F4D5A",
        "originator.type": "NFC",
        "customer_id": "hw-uat"
    }, {
        "timestamp_utc": "2021-03-16 22:29:26",
        "transaction_id": "bf32beaf-09e2-4bae-8dbc-1953fc7f7efa",
        "asset_id": "1G1FY6S03K4108670",
        "timestamp": 1615933766,
        "synthesis.eventSource": "AUTHORIZE_NFC",
        "originator.id": "000000000000000000000000500F4D5A",
        "originator.type": "NFC",
        "customer_id": "hw-uat"
    }, {
        "timestamp_utc": "2021-03-16 22:27:39",
        "transaction_id": "4ee8962f-5fa2-d294-eab7-2b8b8c4b4c31",
        "asset_id": "1G1FY6S03K4108670",
        "timestamp": 1615933659,
        "synthesis.eventSource": "ENGINE_OFF",
        "originator.id": "005102001867",
        "originator.type": "TCU",
        "customer_id": "hw-uat"
    }, {
        "timestamp_utc": "2021-03-16 22:27:33",
        "transaction_id": "468f7c10-814a-9f12-cbc0-743ac0644ec3",
        "asset_id": "1G1FY6S03K4108670",
        "timestamp": 1615933653,
        "synthesis.eventSource": "ENGINE_ON",
        "originator.id": "005102001867",
        "originator.type": "TCU",
        "customer_id": "hw-uat"
    }, {
        "timestamp_utc": "2021-03-16 22:27:06",
        "transaction_id": "d7a0685c-f7be-19b7-29f4-9ef4bfbe3871",
        "asset_id": "1G1FY6S03K4108670",
        "timestamp": 1615933626,
        "synthesis.eventSource": "ENGINE_OFF",
        "originator.id": "005102001867",
        "originator.type": "TCU",
        "customer_id": "hw-uat"
    }, {
        "timestamp_utc": "2021-03-16 22:26:22",
        "transaction_id": "416d6855-f30b-a054-59db-cecb52b5e780",
        "asset_id": "1G1FY6S03K4108670",
        "timestamp": 1615933582,
        "synthesis.eventSource": "ENGINE_ON",
        "originator.id": "005102001867",
        "originator.type": "TCU",
        "customer_id": "hw-uat"
    }, {
        "timestamp_utc": "2021-03-16 22:20:25",
        "transaction_id": "45a17d52-6b7c-4fd1-850b-ff7d628f5559",
        "asset_id": "1G1FY6S03K4108670",
        "timestamp": 1615933225,
        "synthesis.eventSource": "CLEAR_KEYS_REQUESTED",
        "originator.id": "000000000000000000000000500F4D5A",
        "originator.type": "NFC",
        "customer_id": "hw-uat"
    }, {
        "timestamp_utc": "2021-03-16 22:20:05",
        "transaction_id": "27aae0d3-39f8-4904-9e69-d4ce8b0ff35b",
        "asset_id": "1G1FY6S03K4108670",
        "timestamp": 1615933205,
        "synthesis.eventSource": "AUTHORIZE_NFC",
        "originator.id": "000000000000000000000000500F4D5A",
        "originator.type": "NFC",
        "customer_id": "hw-uat"
    }, {
        "timestamp_utc": "2021-03-16 22:19:01",
        "transaction_id": "fe125753-6c15-4acb-8923-02e89940ecd0",
        "asset_id": "1G1FY6S03K4108670",
        "timestamp": 1615933141,
        "synthesis.eventSource": "CLEAR_KEYS",
        "originator.id": null,
        "originator.type": "SERVER",
        "customer_id": "hw-uat"
    }, {
        "timestamp_utc": "2021-03-16 22:17:27",
        "transaction_id": "652fbe95-174c-493c-8e95-92624c2a780c",
        "asset_id": "1G1FY6S03K4108670",
        "timestamp": 1615933047,
        "synthesis.eventSource": "CLEAR_KEYS_REQUESTED",
        "originator.id": "000000000000000000000000500F4D5A",
        "originator.type": "NFC",
        "customer_id": "hw-uat"
    }
]